{"ultimo":0,"hoy":2,"tickets":[{"numero":16,"escritorio":null},{"numero":17,"escritorio":null},{"numero":18,"escritorio":null},{"numero":19,"escritorio":null},{"numero":20,"escritorio":null},{"numero":21,"escritorio":null},{"numero":22,"escritorio":null},{"numero":23,"escritorio":null},{"numero":24,"escritorio":null},{"numero":25,"escritorio":null},{"numero":1,"escritorio":null},{"numero":2,"escritorio":null},{"numero":3,"escritorio":null},{"numero":4,"escritorio":null},{"numero":5,"escritorio":null},{"numero":6,"escritorio":null}],"ultimos4":[{"numero":15,"escritorio":"escritorio1"},{"numero":14,"escritorio":"escritorio1"},{"numero":13,"escritorio":"escritorio1"},{"numero":12,"escritorio":"escritorio1"}]}